jenkins_tui/__init__.py
jenkins_tui/app.py
jenkins_tui/ask.py
jenkins_tui/config.py
jenkins_tui/containers.py
jenkins_tui/jenkins/__init__.py
jenkins_tui/jenkins/api.py
jenkins_tui/renderables/__init__.py
jenkins_tui/renderables/build_history_table.py
jenkins_tui/renderables/button.py
jenkins_tui/renderables/executor_status_table.py
jenkins_tui/renderables/figlet_text.py
jenkins_tui/renderables/help.py
jenkins_tui/renderables/paginated_table.py
jenkins_tui/renderables/text.py
jenkins_tui/styles.py
jenkins_tui/tree.py
jenkins_tui/util.py
jenkins_tui/views/__init__.py
jenkins_tui/views/base.py
jenkins_tui/views/build_with_parameters.py
jenkins_tui/views/home.py
jenkins_tui/views/job.py
jenkins_tui/views/scroll.py
jenkins_tui/views/side_bar.py
jenkins_tui/widgets/__init__.py
jenkins_tui/widgets/button.py
jenkins_tui/widgets/executor_status.py
jenkins_tui/widgets/figlet_text_widget.py
jenkins_tui/widgets/flash.py
jenkins_tui/widgets/help.py
jenkins_tui/widgets/job_details.py
jenkins_tui/widgets/nav.py
jenkins_tui/widgets/scroll_bar.py
jenkins_tui/widgets/search.py
jenkins_tui/widgets/text.py
jenkins_tui/widgets/text_input_field.py
jenkins_tui-0.2.2.dist-info/entry_points.txt
jenkins_tui-0.2.2.dist-info/LICENSE
jenkins_tui-0.2.2.dist-info/WHEEL
jenkins_tui-0.2.2.dist-info/METADATA
jenkins_tui-0.2.2.dist-info/RECORD
