Metadata-Version: 2.1
Name: jenkins-tui
Version: 0.2.2
Summary: An interactive TUI for Jenkins
Home-page: https://github.com/chelnak/jenkins-tui
License: MIT
Author: chelnak
Requires-Python: >=3.9,<4.0
Classifier: License :: OSI Approved :: MIT License
Classifier: Programming Language :: Python :: 3
Classifier: Programming Language :: Python :: 3.10
Classifier: Programming Language :: Python :: 3.9
Requires-Dist: click (>=8.0.3,<9.0.0)
Requires-Dist: dependency-injector (>=4.36.2,<5.0.0)
Requires-Dist: fast-autocomplete[pylev] (>=0.9.0,<0.10.0)
Requires-Dist: httpx (>=0.19.0,<0.20.0)
Requires-Dist: pyfiglet (>=0.8.post1,<0.9)
Requires-Dist: rich (>=10.11.0,<11.0.0)
Requires-Dist: textual (>=0.1.12,<0.2.0)
Requires-Dist: textual-inputs (>=0.1.2,<0.2.0)
Requires-Dist: toml (>=0.10.2,<0.11.0)
Requires-Dist: validators (>=0.18.2,<0.19.0)
